{"metrics": [{"predict_rouge1": 34.8469, "predict_rouge2": 16.2719, "predict_rougeL": 27.332, "predict_rougeLsum": 31.576, "predict_gen_len": 50.54, "predict_runtime": 10.2447, "predict_samples_per_second": 4.881, "predict_steps_per_second": 4.881, "predict_block_avg": 5.999999999999881}, {"predict_rouge1": 34.8469, "predict_rouge2": 16.2719, "predict_rougeL": 27.332, "predict_rougeLsum": 31.576, "predict_gen_len": 50.54, "predict_runtime": 10.2596, "predict_samples_per_second": 4.873, "predict_steps_per_second": 4.873, "predict_block_avg": 5.9999999999999405}, {"predict_rouge1": 35.7454, "predict_rouge2": 16.0088, "predict_rougeL": 27.0787, "predict_rougeLsum": 32.393, "predict_gen_len": 53.02, "predict_runtime": 8.8325, "predict_samples_per_second": 5.661, "predict_steps_per_second": 5.661, "predict_block_avg": 4.192380233873852}, {"predict_rouge1": 35.7454, "predict_rouge2": 16.0088, "predict_rougeL": 27.0787, "predict_rougeLsum": 32.393, "predict_gen_len": 53.02, "predict_runtime": 8.8279, "predict_samples_per_second": 5.664, "predict_steps_per_second": 5.664, "predict_block_avg": 4.192380233873931}, {"predict_rouge1": 35.0204, "predict_rouge2": 15.6239, "predict_rougeL": 27.0998, "predict_rougeLsum": 32.0858, "predict_gen_len": 55.28, "predict_runtime": 8.2375, "predict_samples_per_second": 6.07, "predict_steps_per_second": 6.07, "predict_block_avg": 3.364688856729256}, {"predict_rouge1": 32.1711, "predict_rouge2": 14.3066, "predict_rougeL": 24.751, "predict_rougeLsum": 29.3697, "predict_gen_len": 60.08, "predict_runtime": 7.9086, "predict_samples_per_second": 6.322, "predict_steps_per_second": 6.322, "predict_block_avg": 2.550932090545854}, {"predict_rouge1": 28.7459, "predict_rouge2": 12.3316, "predict_rougeL": 22.4602, "predict_rougeLsum": 26.4343, "predict_gen_len": 70.5, "predict_runtime": 8.5711, "predict_samples_per_second": 5.834, "predict_steps_per_second": 5.834, "predict_block_avg": 2.0034042553190923}, {"predict_rouge1": 24.7847, "predict_rouge2": 9.8647, "predict_rougeL": 19.4562, "predict_rougeLsum": 22.5526, "predict_gen_len": 71.48, "predict_runtime": 8.4091, "predict_samples_per_second": 5.946, "predict_steps_per_second": 5.946, "predict_block_avg": 1.855064353665309}, {"predict_rouge1": 24.5826, "predict_rouge2": 9.3699, "predict_rougeL": 19.419, "predict_rougeLsum": 22.1217, "predict_gen_len": 63.5, "predict_runtime": 7.2714, "predict_samples_per_second": 6.876, "predict_steps_per_second": 6.876, "predict_block_avg": 1.6551181102361683}, {"predict_rouge1": 21.6128, "predict_rouge2": 7.4575, "predict_rougeL": 17.2033, "predict_rougeLsum": 19.9381, "predict_gen_len": 56.64, "predict_runtime": 6.3152, "predict_samples_per_second": 7.917, "predict_steps_per_second": 7.917, "predict_block_avg": 1.4872881355931677}, {"predict_rouge1": 15.7599, "predict_rouge2": 4.4879, "predict_rougeL": 12.3678, "predict_rougeLsum": 14.6563, "predict_gen_len": 71.62, "predict_runtime": 7.524, "predict_samples_per_second": 6.645, "predict_steps_per_second": 6.645, "predict_block_avg": 1.2348506003909177}], "deltas": [0.0, 0.1, 0.2, 0.30000000000000004, 0.4, 0.5, 0.6000000000000001, 0.7000000000000001, 0.8, 0.9, 1.0], "L_vals": [0.0, 0.0, 0.15309923136359704, 0.15309923136359704, 0.24538544009067753, 0.36059555160047774, 0.4695875803730609, 0.561960632056377, 0.6317171980853439, 0.7522745707341199, 0.8449102264430828], "lambdas": [1, 1, 1.0, 1.0, 0.85, 0.6, 0.45, 0.35, 0.25, 0.15, 0.1], "config": {"vocab_size": 32128, "d_model": 512, "d_kv": 64, "d_ff": 2048, "num_layers": 6, "num_decoder_layers": 6, "num_heads": 8, "relative_attention_num_buckets": 32, "relative_attention_max_distance": 128, "dropout_rate": 0.1, "classifier_dropout": 0.0, "layer_norm_epsilon": 1e-06, "initializer_factor": 1.0, "feed_forward_proj": "relu", "use_cache": true, "dense_act_fn": "relu", "is_gated_act": false, "return_dict": true, "output_hidden_states": false, "output_attentions": false, "torchscript": false, "torch_dtype": "float32", "use_bfloat16": false, "tf_legacy_loss": false, "pruned_heads": {}, "tie_word_embeddings": true, "chunk_size_feed_forward": 0, "is_encoder_decoder": true, "is_decoder": false, "cross_attention_hidden_size": null, "add_cross_attention": false, "tie_encoder_decoder": false, "max_length": 20, "min_length": 0, "do_sample": false, "early_stopping": false, "num_beams": 1, "num_beam_groups": 1, "diversity_penalty": 0.0, "temperature": 1.0, "top_k": 50, "top_p": 1.0, "typical_p": 1.0, "repetition_penalty": 1.0, "length_penalty": 1.0, "no_repeat_ngram_size": 0, "encoder_no_repeat_ngram_size": 0, "bad_words_ids": null, "num_return_sequences": 1, "output_scores": false, "return_dict_in_generate": false, "forced_bos_token_id": null, "forced_eos_token_id": null, "remove_invalid_values": false, "exponential_decay_length_penalty": null, "suppress_tokens": null, "begin_suppress_tokens": null, "architectures": ["EffT5ForConditionalGeneration"], "finetuning_task": null, "id2label": {"0": "LABEL_0", "1": "LABEL_1"}, "label2id": {"LABEL_0": 0, "LABEL_1": 1}, "tokenizer_class": null, "prefix": null, "bos_token_id": null, "pad_token_id": 0, "eos_token_id": 1, "sep_token_id": null, "decoder_start_token_id": 0, "task_specific_params": {"summarization": {"early_stopping": true, "length_penalty": 2.0, "max_length": 200, "min_length": 30, "no_repeat_ngram_size": 3, "num_beams": 4, "prefix": "summarize: "}, "translation_en_to_de": {"early_stopping": true, "max_length": 300, "num_beams": 4, "prefix": "translate English to German: "}, "translation_en_to_fr": {"early_stopping": true, "max_length": 300, "num_beams": 4, "prefix": "translate English to French: "}, "translation_en_to_ro": {"early_stopping": true, "max_length": 300, "num_beams": 4, "prefix": "translate English to Romanian: "}}, "problem_type": null, "_name_or_path": "./save/cnndm_t5_small_run2", "transformers_version": "4.41.1", "copy_skipped_hidden_states": false, "distill_layer_alpha": null, "do_layer_transformation": false, "exit_conf_threshold": 0.05, "exit_conf_type": "softmax", "exit_min_layer": 1, "exit_position_temp": null, "intermediate_loss_fn": null, "lora_alpha": 8, "lora_dropout": 0.1, "lora_rank": 8, "lora_target_modules": null, "max_answer_length": 128, "model_type": "t5", "n_positions": 512, "output_hidden_states_decoder": false, "output_past": true, "parallel_causal_mask": true, "parallel_gen_token": true, "rollback_conf_threshold": null, "shallow2deep_conf_threshold": 1.0, "shallow2deep_conf_type": null, "shallow_exit_layer": null, "static_exit_layer": null, "train_meta_cm_head": false, "use_adapt_threshold": false, "use_early_exit": true, "use_lora": false, "use_shallow_deep": false, "use_synchronize": true}}